json_dev_logger-0.0.15.dist-info/licenses/LICENSE
py_logger/__init__.py
py_logger/jsondevlogger.py
json_dev_logger-0.0.15.dist-info/METADATA
json_dev_logger-0.0.15.dist-info/WHEEL
json_dev_logger-0.0.15.dist-info/top_level.txt
json_dev_logger-0.0.15.dist-info/RECORD
