Metadata-Version: 2.4
Name: json-dev-logger
Version: 0.0.15
Summary: json logger, very helpful for developers at developing stage
Author-email: Areso <returnstrike@yandex.com>
License-Expression: MIT
Project-URL: Homepage, https://github.com/Areso/py_logger
Classifier: Programming Language :: Python :: 3
Classifier: Operating System :: POSIX :: Linux
Requires-Python: >=3.7
License-File: LICENSE
Dynamic: license-file
